pocketcasts/__init__.py
pocketcasts/api.py
pocketcasts/episode.py
pocketcasts/podcast.py
pocketcasts_api-0.2.0.dist-info/DESCRIPTION.rst
pocketcasts_api-0.2.0.dist-info/METADATA
pocketcasts_api-0.2.0.dist-info/RECORD
pocketcasts_api-0.2.0.dist-info/WHEEL
pocketcasts_api-0.2.0.dist-info/metadata.json
pocketcasts_api-0.2.0.dist-info/top_level.txt
