Metadata-Version: 2.0
Name: pocketcasts-api
Version: 0.2.0
Summary: Unofficial API for pocketcasts.com
Home-page: https://github.com/exofudge/Pocket-Casts
Author: Fergus Longley
Author-email: ferguslongley@live.com
License: MIT
Keywords: podcasts pocketcasts
Platform: UNKNOWN
Classifier: Development Status :: 4 - Beta
Classifier: License :: OSI Approved :: MIT License
Classifier: Programming Language :: Python :: 3.5
Requires-Dist: requests
